stack_gen/__init__.py
stack_gen/main.py
tests/__init__.py
stack_gen-0.0.19.dist-info/METADATA
stack_gen-0.0.19.dist-info/WHEEL
stack_gen-0.0.19.dist-info/entry_points.txt
stack_gen-0.0.19.dist-info/top_level.txt
stack_gen-0.0.19.dist-info/RECORD
