Metadata-Version: 2.1
Name: stack_gen
Version: 0.0.19
Summary: A CLI tool to generate code base from any cookiecutter template
Home-page: 
Author: Devoteam digital lab
Author-email: valdo.negou.tawembe@devoteamgcloud.com
License: MIT
Classifier: Programming Language :: Python :: 3.11
Classifier: Operating System :: OS Independent
Requires-Python: >=3.7
Requires-Dist: click ==8.1.7
Requires-Dist: loguru ==0.7.2
